pyrate/__init__.py
pyrate/main.py
pyrate/scripts/__init__.py
pyrate/scripts/cliutils.py
pyrate/services/__init__.py
pyrate/services/basecamp.py
pyrate/services/constantcontact.py
pyrate/services/github.py
pyrate/services/harvest.py
pyrate/services/mailchimp.py
pyrate/services/twitter.py
pyrate/tests/__init__.py
pyrate/tests/tests.py
pyrate/utils/__init__.py
pyrate-0.5a9.dist-info/DESCRIPTION.rst
pyrate-0.5a9.dist-info/METADATA
pyrate-0.5a9.dist-info/RECORD
pyrate-0.5a9.dist-info/WHEEL
pyrate-0.5a9.dist-info/entry_points.txt
pyrate-0.5a9.dist-info/metadata.json
pyrate-0.5a9.dist-info/top_level.txt
