Metadata-Version: 2.0
Name: pyrate
Version: 0.5a9
Summary: Pyrate is a python wrapper for restful web apis. It's like magic but simpler.
Home-page: https://github.com/chive/pyrate
Author: Kim Thoenen
Author-email: kim@smuzey.ch
License: MIT
Platform: OS Independent
Classifier: Development Status :: 4 - Beta
Classifier: Environment :: Console
Classifier: Environment :: Web Environment
Classifier: Intended Audience :: Developers
Classifier: License :: OSI Approved :: MIT License
Classifier: Natural Language :: English
Classifier: Operating System :: OS Independent
Classifier: Programming Language :: Python
Classifier: Programming Language :: Python :: 2
Classifier: Programming Language :: Python :: 3
Classifier: Topic :: Communications
Classifier: Topic :: Internet :: WWW/HTTP :: Dynamic Content
Requires-Dist: requests
Requires-Dist: requests-oauthlib
Requires-Dist: six
